gro_exp/__init__.py
gro_exp/utils.py
tests/__init__.py
tests/test_simple.py
gro_exp-0.0.3.dist-info/METADATA
gro_exp-0.0.3.dist-info/WHEEL
gro_exp-0.0.3.dist-info/top_level.txt
gro_exp-0.0.3.dist-info/RECORD
