Metadata-Version: 2.1
Name: gro-exp
Version: 0.0.3
Summary: description
Home-page: https://github.com/marc310896/utils
Download-URL: https://github.com/marc310896/utils/archive/refs/tags/0.0.1.tar.gz
Author: Marc Hoegler
Author-email: marc.hoegler@icvt.uni-stuttgart.de
License: UNKNOWN
Platform: UNKNOWN
Requires-Python: >=3.5
Requires-Dist: numpy
Requires-Dist: pandas
Requires-Dist: seaborn
Requires-Dist: xlrd
